fastfame/__init__.py
fastfame/__main__.py
fastfame/client.py
fastfame-1.0.2.dist-info/METADATA
fastfame-1.0.2.dist-info/WHEEL
fastfame-1.0.2.dist-info/top_level.txt
fastfame-1.0.2.dist-info/RECORD
