Metadata-Version: 2.4
Name: fastfame
Version: 1.0.2
Summary: Official FastFame API client for TikTok views
Author-email: REAPXR <support@fastfame.pro>
License: Proprietary
Project-URL: Homepage, https://fastfame.pro
Requires-Python: >=3.8
Requires-Dist: requests
